{
  "as_of": "2026-07-08T12:08:27+05:30",
  "checkpoint": "mid",
  "open_escalations": [
    {
      "symbol": "ITC.NS",
      "severity": "MEDIUM",
      "action_type": "BLOCKED_BY_DATA_QUALITY",
      "reason": "No usable quote — provider issue.",
      "trigger_ids": [
        "trg_8d90ff2d9d51"
      ],
      "action_status": "OPEN",
      "focused_analysis_required": false,
      "focused_analysis_result": null,
      "manual_review_required": false,
      "email_sent": false,
      "final_decision": "No action — data not trustworthy.",
      "escalation_id": "esc_c4c5b371a780",
      "created_at": "2026-07-08T12:08:27+05:30",
      "expires_at": "2026-07-08T12:08:27+05:30"
    },
    {
      "symbol": "RELIANCE.NS",
      "severity": "MEDIUM",
      "action_type": "BLOCKED_BY_DATA_QUALITY",
      "reason": "No usable quote — provider issue.",
      "trigger_ids": [
        "trg_f6645644b3ad"
      ],
      "action_status": "OPEN",
      "focused_analysis_required": false,
      "focused_analysis_result": null,
      "manual_review_required": false,
      "email_sent": false,
      "final_decision": "No action — data not trustworthy.",
      "escalation_id": "esc_077ccdb305cf",
      "created_at": "2026-07-08T12:08:27+05:30",
      "expires_at": "2026-07-08T12:08:27+05:30"
    },
    {
      "symbol": "HDFCBANK.NS",
      "severity": "MEDIUM",
      "action_type": "BLOCKED_BY_DATA_QUALITY",
      "reason": "No usable quote — provider issue.",
      "trigger_ids": [
        "trg_ace8074af4a6"
      ],
      "action_status": "OPEN",
      "focused_analysis_required": false,
      "focused_analysis_result": null,
      "manual_review_required": false,
      "email_sent": false,
      "final_decision": "No action — data not trustworthy.",
      "escalation_id": "esc_95c968d19abc",
      "created_at": "2026-07-08T12:08:27+05:30",
      "expires_at": "2026-07-08T12:08:27+05:30"
    },
    {
      "symbol": "INFY.NS",
      "severity": "MEDIUM",
      "action_type": "BLOCKED_BY_DATA_QUALITY",
      "reason": "No usable quote — provider issue.",
      "trigger_ids": [
        "trg_5bef273a9e7f"
      ],
      "action_status": "OPEN",
      "focused_analysis_required": false,
      "focused_analysis_result": null,
      "manual_review_required": false,
      "email_sent": false,
      "final_decision": "No action — data not trustworthy.",
      "escalation_id": "esc_d5dc3ed0936f",
      "created_at": "2026-07-08T12:08:27+05:30",
      "expires_at": "2026-07-08T12:08:27+05:30"
    },
    {
      "symbol": "TCS.NS",
      "severity": "MEDIUM",
      "action_type": "BLOCKED_BY_DATA_QUALITY",
      "reason": "No usable quote — provider issue.",
      "trigger_ids": [
        "trg_432c1ed52983"
      ],
      "action_status": "OPEN",
      "focused_analysis_required": false,
      "focused_analysis_result": null,
      "manual_review_required": false,
      "email_sent": false,
      "final_decision": "No action — data not trustworthy.",
      "escalation_id": "esc_23a839612346",
      "created_at": "2026-07-08T12:08:27+05:30",
      "expires_at": "2026-07-08T12:08:27+05:30"
    }
  ],
  "actions_taken": [],
  "blocked_actions": [
    {
      "symbol": "ITC.NS",
      "blocked_by": "DATA_QUALITY",
      "trigger": "PROVIDER_FAILURE"
    },
    {
      "symbol": "RELIANCE.NS",
      "blocked_by": "DATA_QUALITY",
      "trigger": "PROVIDER_FAILURE"
    },
    {
      "symbol": "HDFCBANK.NS",
      "blocked_by": "DATA_QUALITY",
      "trigger": "PROVIDER_FAILURE"
    },
    {
      "symbol": "INFY.NS",
      "blocked_by": "DATA_QUALITY",
      "trigger": "PROVIDER_FAILURE"
    },
    {
      "symbol": "TCS.NS",
      "blocked_by": "DATA_QUALITY",
      "trigger": "PROVIDER_FAILURE"
    }
  ]
}